{
  "name": "terraform-module-builder",
  "displayName": "Terraform Module Builder",
  "category": "devops",
  "type": "standard",
  "description": "Build reusable Terraform modules",
  "version": "2025.0.0",
  "author": {
    "name": "Andrew Nixdorf",
    "email": "[email protected]"
  },
  "repository": "https://github.com/AndroidNextdoor/stoked-automations/tree/main/./plugins/devops/terraform-module-builder",
  "license": "MIT",
  "keywords": [
    "terraform",
    "iac",
    "modules",
    "infrastructure",
    "devops"
  ],
  "features": [],
  "installation": "/plugin install terraform-module-builder@stoked-automations",
  "usage": {},
  "examples": [],
  "screenshots": [],
  "documentation": "https://github.com/AndroidNextdoor/stoked-automations/blob/main/./plugins/devops/terraform-module-builder/README.md",
  "tags": [
    "terraform",
    "iac",
    "modules",
    "infrastructure",
    "devops"
  ],
  "featured": false,
  "verified": true,
  "downloads": 0,
  "rating": 0,
  "reviews": [],
  "createdAt": "2025-10-19T02:38:21.035Z",
  "updatedAt": "2025-10-19T02:38:21.035Z"
}